dtag/__init__.py
dtag/documents.py
dtag/files.py
dtag-0.0.1.dist-info/METADATA
dtag-0.0.1.dist-info/WHEEL
dtag-0.0.1.dist-info/top_level.txt
dtag-0.0.1.dist-info/RECORD
